gstflow_interface/__init__.py
gstflow_interface/core.py
gstflow_interface/lowlevel.py
gstflow_interface/types.py
gstflow_interface/bin/__init__.py
gstflow_interface/include/__init__.py
gstflow_interface/include/gstflow_user_api.h
gstflow_interface/lib/__init__.py
gstflow_interface-1.1.0.dist-info/licenses/LICENSE
gstflow_interface-1.1.0.dist-info/METADATA
gstflow_interface-1.1.0.dist-info/WHEEL
gstflow_interface-1.1.0.dist-info/top_level.txt
gstflow_interface-1.1.0.dist-info/RECORD
