Metadata-Version: 2.4
Name: gstflow_interface
Version: 1.1.0
Summary: Python interface for interacting with native C/C++ libraries with defined Gstflow function signature
Author-email: Mohd Yusuf <yusuf.intelligentedgesystems@gmail.com>
License: MIT
Keywords: deepstream,gstreamer,automation,ai,artificial intelligence,computer vision,edge,intelligent edge,craftifai,intelligent edge systems,ies,nvidia,jetson,inference,opencv
Requires-Python: >=3.7
License-File: LICENSE
Requires-Dist: numpy
Dynamic: license-file
